{
  "date": "2026-04-25",
  "ranks": {
    "1": 2,
    "2": 1,
    "3": 3,
    "4": 4,
    "5": 9,
    "6": 8,
    "7": 5,
    "8": 7,
    "9": 6,
    "10": 10,
    "11": 11,
    "12": 15,
    "13": 13,
    "14": 14,
    "15": 28,
    "16": 12,
    "17": 63,
    "18": 80,
    "19": 137,
    "20": 25,
    "21": 18,
    "22": 19,
    "23": 17,
    "24": 22,
    "25": 40,
    "26": 34,
    "27": 24,
    "28": 27,
    "29": 21,
    "30": 20,
    "31": 99,
    "32": 32,
    "33": 29,
    "34": 39,
    "35": 156,
    "36": 16,
    "37": 37,
    "38": 49,
    "39": 92,
    "40": 146,
    "41": 65,
    "42": 41,
    "43": 52,
    "44": 35,
    "45": 55,
    "46": 46,
    "47": 30,
    "48": 93,
    "49": 82,
    "50": 103,
    "51": 51,
    "52": 52,
    "53": 98,
    "54": 56,
    "55": 33,
    "56": 45,
    "57": 97,
    "58": 101,
    "59": 125,
    "60": 116,
    "61": 91,
    "62": 78,
    "63": 195,
    "64": 36,
    "65": 85,
    "66": 66,
    "67": 62,
    "68": 188,
    "69": 31,
    "70": 88,
    "71": 178,
    "72": 72,
    "73": 181,
    "74": 153,
    "75": 75,
    "76": 76,
    "77": 143,
    "78": 165,
    "79": 174,
    "80": 80,
    "81": 115,
    "82": 111,
    "83": 135,
    "84": 76,
    "85": 85,
    "86": 138,
    "87": 74,
    "88": 88,
    "89": 132,
    "90": 90,
    "91": 147,
    "92": 92,
    "93": 93,
    "94": 67,
    "95": 95,
    "96": 35,
    "97": 97,
    "98": 175,
    "99": 99,
    "100": 121
  },
  "_note": "Rank-move baseline \u2014 rolls forward every BASELINE_TTL_DAYS days. Not edited by hand."
}